tempmailio/__init__.py
tempmailio/tempmailio.py
tempmailio/tempmailio_api.py
tempmailio/models/__init__.py
tempmailio/models/domain.py
tempmailio/models/email.py
tempmailio/models/email_address.py
tempmailio-0.0.4.dist-info/LICENSE
tempmailio-0.0.4.dist-info/METADATA
tempmailio-0.0.4.dist-info/WHEEL
tempmailio-0.0.4.dist-info/top_level.txt
tempmailio-0.0.4.dist-info/RECORD
