Metadata-Version: 2.1
Name: tempmailio
Version: 0.0.4
Summary: python wrapper for tempmail.io
Home-page: https://github.com/kkristof200/py_tempmailio
Author: Kristof
License: UNKNOWN
Platform: UNKNOWN
Classifier: Programming Language :: Python :: 3
Classifier: License :: OSI Approved :: MIT License
Classifier: Operating System :: OS Independent
Requires-Python: >=3.5
Requires-Dist: jsoncodable
Requires-Dist: kcu
